sag_py_fastapi_request_id/__init__.py
sag_py_fastapi_request_id/models.py
sag_py_fastapi_request_id/py.typed
sag_py_fastapi_request_id/request_context.py
sag_py_fastapi_request_id/request_context_logging_filter.py
sag_py_fastapi_request_id/request_context_middleware.py
sag_py_fastapi_request_id-1.0.3.dist-info/licenses/LICENSE.txt
sag_py_fastapi_request_id-1.0.3.dist-info/METADATA
sag_py_fastapi_request_id-1.0.3.dist-info/WHEEL
sag_py_fastapi_request_id-1.0.3.dist-info/top_level.txt
sag_py_fastapi_request_id-1.0.3.dist-info/RECORD
